bcpscrapper/__init__.py
bcpscraper-0.0.2.dist-info/.gitignore
bcpscraper-0.0.2.dist-info/LICENSE.txt
bcpscraper-0.0.2.dist-info/METADATA
bcpscraper-0.0.2.dist-info/WHEEL
bcpscraper-0.0.2.dist-info/top_level.txt
bcpscraper-0.0.2.dist-info/RECORD
